tinygp/__init__.py
tinygp/gp.py
tinygp/helpers.py
tinygp/means.py
tinygp/noise.py
tinygp/numpyro_support.py
tinygp/py.typed
tinygp/test_utils.py
tinygp/tinygp_version.py
tinygp/transforms.py
tinygp/kernels/__init__.py
tinygp/kernels/base.py
tinygp/kernels/distance.py
tinygp/kernels/quasisep.py
tinygp/kernels/stationary.py
tinygp/solvers/__init__.py
tinygp/solvers/direct.py
tinygp/solvers/kalman.py
tinygp/solvers/solver.py
tinygp/solvers/quasisep/__init__.py
tinygp/solvers/quasisep/core.py
tinygp/solvers/quasisep/general.py
tinygp/solvers/quasisep/ops.py
tinygp/solvers/quasisep/solver.py
tinygp-0.3.0.dist-info/METADATA
tinygp-0.3.0.dist-info/WHEEL
tinygp-0.3.0.dist-info/licenses/LICENSE
tinygp-0.3.0.dist-info/RECORD
