Metadata-Version: 2.1
Name: tinygp
Version: 0.3.0
Summary: The tiniest of Gaussian Process libraries
Author-email: Dan Foreman-Mackey <foreman.mackey@gmail.com>
License: MIT
License-File: LICENSE
Classifier: Development Status :: 4 - Beta
Classifier: Intended Audience :: Developers
Classifier: Intended Audience :: Science/Research
Classifier: License :: OSI Approved :: MIT License
Classifier: Operating System :: OS Independent
Classifier: Programming Language :: Python
Classifier: Programming Language :: Python :: 3
Requires-Python: >=3.9
Requires-Dist: equinox
Requires-Dist: jax
Requires-Dist: jaxlib
Provides-Extra: comparison
Requires-Dist: celerite; extra == 'comparison'
Requires-Dist: george; extra == 'comparison'
Provides-Extra: docs
Requires-Dist: arviz; extra == 'docs'
Requires-Dist: flax; extra == 'docs'
Requires-Dist: ipython; extra == 'docs'
Requires-Dist: jaxopt; extra == 'docs'
Requires-Dist: matplotlib; extra == 'docs'
Requires-Dist: myst-nb; extra == 'docs'
Requires-Dist: numpyro; extra == 'docs'
Requires-Dist: optax; extra == 'docs'
Requires-Dist: sphinx-book-theme; extra == 'docs'
Requires-Dist: statsmodels; extra == 'docs'
Provides-Extra: test
Requires-Dist: pytest; extra == 'test'
